kubernetes_kernel_provider/__init__.py
kubernetes_kernel_provider/_version.py
kubernetes_kernel_provider/k8s.py
kubernetes_kernel_provider/kernelspecapp.py
kubernetes_kernel_provider/provider.py
kubernetes_kernel_provider/kernelspecs/k8skp_python/k8skp_kernel.json
kubernetes_kernel_provider/kernelspecs/k8skp_python_spark/k8skp_kernel.json
kubernetes_kernel_provider/kernelspecs/k8skp_python_spark/bin/run.sh
kubernetes_kernel_provider/kernelspecs/k8skp_python_tf/k8skp_kernel.json
kubernetes_kernel_provider/kernelspecs/k8skp_r/k8skp_kernel.json
kubernetes_kernel_provider/kernelspecs/k8skp_r_spark/k8skp_kernel.json
kubernetes_kernel_provider/kernelspecs/k8skp_r_spark/bin/run.sh
kubernetes_kernel_provider/kernelspecs/k8skp_scala/k8skp_kernel.json
kubernetes_kernel_provider/kernelspecs/k8skp_scala_spark/k8skp_kernel.json
kubernetes_kernel_provider/kernelspecs/k8skp_scala_spark/bin/run.sh
kubernetes_kernel_provider/pod-launcher/scripts/kernel-pod.yaml.j2
kubernetes_kernel_provider/pod-launcher/scripts/launch_kubernetes.py
kubernetes_kernel_provider/tests/test_kernelspec_app.py
kubernetes_kernel_provider-0.2.0.dist-info/LICENSE
kubernetes_kernel_provider-0.2.0.dist-info/METADATA
kubernetes_kernel_provider-0.2.0.dist-info/WHEEL
kubernetes_kernel_provider-0.2.0.dist-info/entry_points.txt
kubernetes_kernel_provider-0.2.0.dist-info/top_level.txt
kubernetes_kernel_provider-0.2.0.dist-info/RECORD
